algopytest/__init__.py
algopytest/account_ops.py
algopytest/client_ops.py
algopytest/config_params.py
algopytest/entities.py
algopytest/fixtures.py
algopytest/smart_program_ops.py
algopytest/transaction_ops.py
algopytest/type_stubs.py
algopytest/utils.py
algopytest_framework-2.0.0.dist-info/LICENSE
algopytest_framework-2.0.0.dist-info/METADATA
algopytest_framework-2.0.0.dist-info/WHEEL
algopytest_framework-2.0.0.dist-info/entry_points.txt
algopytest_framework-2.0.0.dist-info/top_level.txt
algopytest_framework-2.0.0.dist-info/RECORD
