Metadata-Version: 2.1
Name: algopytest-framework
Version: 2.0.0
Summary: AlgoPytest is a framework which hides away all of the complexity and repetitiveness that comes with testing Algorand Smart Contracts.
Home-page: https://github.com/DamianB-BitFlipper/algopytest.git
Download-URL: https://github.com/DamianB-BitFlipper/algopytest/archive/refs/tags/v2.0.0.tar.gz
Author: Damian Barabonkov
Author-email: damianb@alum.mit.edu
License: MIT
Keywords: Algorand,Smart Contract,Pytest,Unit Tests,Test Suite
Classifier: Framework :: Pytest
Classifier: Intended Audience :: Developers
Classifier: Topic :: Software Development :: Testing :: Unit
Classifier: License :: OSI Approved :: MIT License
Classifier: Programming Language :: Python :: 3
Classifier: Programming Language :: Python :: 3.7
Classifier: Programming Language :: Python :: 3.8
Classifier: Programming Language :: Python :: 3.9
Classifier: Programming Language :: Python :: 3.10
Classifier: Programming Language :: Python :: 3.11
License-File: LICENSE
Requires-Dist: pytest
Requires-Dist: py-algorand-sdk (>=2.0.0)
Requires-Dist: pyteal
Requires-Dist: typing-extensions
